mth_3-1.0.6.data/data/test_version_powerhouse_helper/GameGooseKiller/Game_goose.py
mth_3-1.0.6.data/data/test_version_powerhouse_helper/GameGooseKiller/font/UA Propisi.ttf
mth_3-1.0.6.data/data/test_version_powerhouse_helper/GameGooseKiller/image/Farm-Goose.ico
mth_3-1.0.6.data/data/test_version_powerhouse_helper/GameGooseKiller/image/background.png
mth_3-1.0.6.data/data/test_version_powerhouse_helper/GameGooseKiller/image/bonus.png
mth_3-1.0.6.data/data/test_version_powerhouse_helper/GameGooseKiller/image/boom.png
mth_3-1.0.6.data/data/test_version_powerhouse_helper/GameGooseKiller/image/enemy.png
mth_3-1.0.6.data/data/test_version_powerhouse_helper/GameGooseKiller/image/gameover.png
mth_3-1.0.6.data/data/test_version_powerhouse_helper/GameGooseKiller/image/Goose/1-1.png
mth_3-1.0.6.data/data/test_version_powerhouse_helper/GameGooseKiller/image/Goose/1-2.png
mth_3-1.0.6.data/data/test_version_powerhouse_helper/GameGooseKiller/image/Goose/1-3.png
mth_3-1.0.6.data/data/test_version_powerhouse_helper/GameGooseKiller/image/Goose/1-4.png
mth_3-1.0.6.data/data/test_version_powerhouse_helper/GameGooseKiller/image/Goose/1-5.png
mth_3-1.0.6.data/data/test_version_powerhouse_helper/GameGooseKiller/image/background/1-1.png
mth_3-1.0.6.data/data/test_version_powerhouse_helper/GameGooseKiller/image/background/1-2.png
mth_3-1.0.6.data/data/test_version_powerhouse_helper/GameGooseKiller/image/background/1-3.png
test_version_powerhouse_helper/Address_Book_Handler.py
test_version_powerhouse_helper/Note.py
test_version_powerhouse_helper/Note_Book_Handler.py
test_version_powerhouse_helper/Snake.py
test_version_powerhouse_helper/Sort_Files.py
test_version_powerhouse_helper/__init__.py
test_version_powerhouse_helper/addressbook.py
test_version_powerhouse_helper/addressbook_data.py
test_version_powerhouse_helper/main.py
test_version_powerhouse_helper/Сalculator.py
test_version_powerhouse_helper/GameGooseKiller/Game_goose.py
mth_3-1.0.6.dist-info/LICENSE
mth_3-1.0.6.dist-info/METADATA
mth_3-1.0.6.dist-info/WHEEL
mth_3-1.0.6.dist-info/entry_points.txt
mth_3-1.0.6.dist-info/top_level.txt
mth_3-1.0.6.dist-info/RECORD
